LICENSE.txt
MANIFEST.in
README.txt
setup.cfg
setup.py
biblio/__init__.py
biblio.webquery.egg-info/PKG-INFO
biblio.webquery.egg-info/SOURCES.txt
biblio.webquery.egg-info/dependency_links.txt
biblio.webquery.egg-info/entry_points.txt
biblio.webquery.egg-info/namespace_packages.txt
biblio.webquery.egg-info/not-zip-safe
biblio.webquery.egg-info/requires.txt
biblio.webquery.egg-info/top_level.txt
biblio/webquery/__init__.py
biblio/webquery/basewebquery.py
biblio/webquery/bibrecord.py
biblio/webquery/errors.py
biblio/webquery/impl.py
biblio/webquery/isbndb.py
biblio/webquery/loc.py
biblio/webquery/querythrottle.py
biblio/webquery/utils.py
biblio/webquery/xisbn.py
biblio/webquery/scripts/__init__.py
biblio/webquery/scripts/common.py
biblio/webquery/scripts/config.py
biblio/webquery/scripts/queryisbn.py
biblio/webquery/scripts/renamebyisbn.py
docs/.DS_Store
docs/.svn
docs/HISTORY.txt
docs/api/html/api-objects.txt
docs/api/html/biblio.webquery-module.html
docs/api/html/biblio.webquery-pysrc.html
docs/api/html/biblio.webquery.basewebquery-module.html
docs/api/html/biblio.webquery.basewebquery-pysrc.html
docs/api/html/biblio.webquery.basewebquery.BaseKeyedWebQuery-class.html
docs/api/html/biblio.webquery.basewebquery.BaseWebquery-class.html
docs/api/html/biblio.webquery.bibrecord-module.html
docs/api/html/biblio.webquery.bibrecord-pysrc.html
docs/api/html/biblio.webquery.bibrecord.BibRecord-class.html
docs/api/html/biblio.webquery.bibrecord.PersonalName-class.html
docs/api/html/biblio.webquery.errors-module.html
docs/api/html/biblio.webquery.errors-pysrc.html
docs/api/html/biblio.webquery.errors.ParseError-class.html
docs/api/html/biblio.webquery.errors.QueryError-class.html
docs/api/html/biblio.webquery.errors.QueryThrottleError-class.html
docs/api/html/biblio.webquery.impl-module.html
docs/api/html/biblio.webquery.impl-pysrc.html
docs/api/html/biblio.webquery.impl.ReprObj-class.html
docs/api/html/biblio.webquery.isbndb-module.html
docs/api/html/biblio.webquery.isbndb-pysrc.html
docs/api/html/biblio.webquery.isbndb.IsbndbQuery-class.html
docs/api/html/biblio.webquery.loc-module.html
docs/api/html/biblio.webquery.loc-pysrc.html
docs/api/html/biblio.webquery.loc.LocQuery-class.html
docs/api/html/biblio.webquery.querythrottle-module.html
docs/api/html/biblio.webquery.querythrottle-pysrc.html
