Metadata-Version: 1.0
Name: biblio.webquery
Version: 0.4.3b
Summary: Extracting bibliographic information from web services
Home-page: http://www.agapow.net/software/biblio.webquery
Author: Paul-Michael Agapow
Author-email: agapow@bbsrc.ac.uk
License: BSD
Keywords: web-service REST book
Platform: UNKNOWN
Classifier: Programming Language :: Python
Classifier: Topic :: Software Development :: Libraries :: Python Modules
